calculate_discount_tax/__init__.py
calculate_discount_tax/calculateDiscountTax.py
calculatediscounttax-0.4.0.dist-info/METADATA
calculatediscounttax-0.4.0.dist-info/WHEEL
calculatediscounttax-0.4.0.dist-info/top_level.txt
calculatediscounttax-0.4.0.dist-info/RECORD
