Metadata-Version: 2.4
Name: calculateDiscountTax
Version: 0.4.0
Summary: A simple Python library used to calculate the final amount for the given tax rate or discount rate.
Author: Nidhi Anandan
Author-email: x23286873@student.ncirl.ie
License: MIT
Requires-Python: >=3.7
Dynamic: author
Dynamic: author-email
Dynamic: description
Dynamic: description-content-type
Dynamic: license
Dynamic: requires-python
Dynamic: summary
